Workbook

Sheet Summary
A1: Questbase QA sweep
A2: Build 5ed3f48
A3: Set Result on the Checklist sheet; these totals follow automatically.
A5: Overall | B5: Count
A6: Pass | B6: =COUNTIF(Checklist!$G$2:$G$151,"Pass") -> 0
A7: Fail | B7: =COUNTIF(Checklist!$G$2:$G$151,"Fail") -> 0
A8: Blocked | B8: =COUNTIF(Checklist!$G$2:$G$151,"Blocked") -> 0
A9: Not tested | B9: =COUNTIF(Checklist!$G$2:$G$151,"Not tested") -> 114
A10: N/A | B10: =COUNTIF(Checklist!$G$2:$G$151,"N/A") -> 5
A11: Total checks | B11: 119
A13: By section | B13: Pass | C13: Fail | D13: Blocked | E13: Not tested | F13: Total
A14: Before you start | B14: =COUNTIFS(Checklist!$B$2:$B$151,"Before you start",Checklist!$G$2:$G$151,"Pass") -> 0 | C14: =COUNTIFS(Checklist!$B$2:$B$151,"Before you start",Checklist!$G$2:$G$151,"Fail") -> 0 | D14: =COUNTIFS(Checklist!$B$2:$B$151,"Before you start",Checklist!$G$2:$G$151,"Blocked") -> 0 | E14: =COUNTIFS(Checklist!$B$2:$B$151,"Before you start",Checklist!$G$2:$G$151,"Not tested") -> 4 | F14: =COUNTIF(Checklist!$B$2:$B$151,"Before you start") -> 4
A15: Smoke — every route loads | B15: =COUNTIFS(Checklist!$B$2:$B$151,"Smoke — every route loads",Checklist!$G$2:$G$151,"Pass") -> 0 | C15: =COUNTIFS(Checklist!$B$2:$B$151,"Smoke — every route loads",Checklist!$G$2:$G$151,"Fail") -> 0 | D15: =COUNTIFS(Checklist!$B$2:$B$151,"Smoke — every route loads",Checklist!$G$2:$G$151,"Blocked") -> 0 | E15: =COUNTIFS(Checklist!$B$2:$B$151,"Smoke — every route loads",Checklist!$G$2:$G$151,"Not tested") -> 21 | F15: =COUNTIF(Checklist!$B$2:$B$151,"Smoke — every route loads") -> 21
A16: Shipped in the last two days | B16: =COUNTIFS(Checklist!$B$2:$B$151,"Shipped in the last two days",Checklist!$G$2:$G$151,"Pass") -> 0 | C16: =COUNTIFS(Checklist!$B$2:$B$151,"Shipped in the last two days",Checklist!$G$2:$G$151,"Fail") -> 0 | D16: =COUNTIFS(Checklist!$B$2:$B$151,"Shipped in the last two days",Checklist!$G$2:$G$151,"Blocked") -> 0 | E16: =COUNTIFS(Checklist!$B$2:$B$151,"Shipped in the last two days",Checklist!$G$2:$G$151,"Not tested") -> 21 | F16: =COUNTIF(Checklist!$B$2:$B$151,"Shipped in the last two days") -> 21
A17: Destructive and password-gated | B17: =COUNTIFS(Checklist!$B$2:$B$151,"Destructive and password-gated",Checklist!$G$2:$G$151,"Pass") -> 0 | C17: =COUNTIFS(Checklist!$B$2:$B$151,"Destructive and password-gated",Checklist!$G$2:$G$151,"Fail") -> 0 | D17: =COUNTIFS(Checklist!$B$2:$B$151,"Destructive and password-gated",Checklist!$G$2:$G$151,"Blocked") -> 0 | E17: =COUNTIFS(Checklist!$B$2:$B$151,"Destructive and password-gated",Checklist!$G$2:$G$151,"Not tested") -> 14 | F17: =COUNTIF(Checklist!$B$2:$B$151,"Destructive and password-gated") -> 14
A18: Quest CRM | B18: =COUNTIFS(Checklist!$B$2:$B$151,"Quest CRM",Checklist!$G$2:$G$151,"Pass") -> 0 | C18: =COUNTIFS(Checklist!$B$2:$B$151,"Quest CRM",Checklist!$G$2:$G$151,"Fail") -> 0 | D18: =COUNTIFS(Checklist!$B$2:$B$151,"Quest CRM",Checklist!$G$2:$G$151,"Blocked") -> 0 | E18: =COUNTIFS(Checklist!$B$2:$B$151,"Quest CRM",Checklist!$G$2:$G$151,"Not tested") -> 9 | F18: =COUNTIF(Checklist!$B$2:$B$151,"Quest CRM") -> 9
A19: Workspace and App Builder | B19: =COUNTIFS(Checklist!$B$2:$B$151,"Workspace and App Builder",Checklist!$G$2:$G$151,"Pass") -> 0 | C19: =COUNTIFS(Checklist!$B$2:$B$151,"Workspace and App Builder",Checklist!$G$2:$G$151,"Fail") -> 0 | D19: =COUNTIFS(Checklist!$B$2:$B$151,"Workspace and App Builder",Checklist!$G$2:$G$151,"Blocked") -> 0 | E19: =COUNTIFS(Checklist!$B$2:$B$151,"Workspace and App Builder",Checklist!$G$2:$G$151,"Not tested") -> 11 | F19: =COUNTIF(Checklist!$B$2:$B$151,"Workspace and App Builder") -> 11
A20: Operations, finance and estimating | B20: =COUNTIFS(Checklist!$B$2:$B$151,"Operations, finance and estimating",Checklist!$G$2:$G$151,"Pass") -> 0 | C20: =COUNTIFS(Checklist!$B$2:$B$151,"Operations, finance and estimating",Checklist!$G$2:$G$151,"Fail") -> 0 | D20: =COUNTIFS(Checklist!$B$2:$B$151,"Operations, finance and estimating",Checklist!$G$2:$G$151,"Blocked") -> 0 | E20: =COUNTIFS(Checklist!$B$2:$B$151,"Operations, finance and estimating",Checklist!$G$2:$G$151,"Not tested") -> 10 | F20: =COUNTIF(Checklist!$B$2:$B$151,"Operations, finance and estimating") -> 10
A21: Messages, notifications and search | B21: =COUNTIFS(Checklist!$B$2:$B$151,"Messages, notifications and search",Checklist!$G$2:$G$151,"Pass") -> 0 | C21: =COUNTIFS(Checklist!$B$2:$B$151,"Messages, notifications and search",Checklist!$G$2:$G$151,"Fail") -> 0 | D21: =COUNTIFS(Checklist!$B$2:$B$151,"Messages, notifications and search",Checklist!$G$2:$G$151,"Blocked") -> 0 | E21: =COUNTIFS(Checklist!$B$2:$B$151,"Messages, notifications and search",Checklist!$G$2:$G$151,"Not tested") -> 7 | F21: =COUNTIF(Checklist!$B$2:$B$151,"Messages, notifications and search") -> 7
A22: Company, users and platform | B22: =COUNTIFS(Checklist!$B$2:$B$151,"Company, users and platform",Checklist!$G$2:$G$151,"Pass") -> 0 | C22: =COUNTIFS(Checklist!$B$2:$B$151,"Company, users and platform",Checklist!$G$2:$G$151,"Fail") -> 0 | D22: =COUNTIFS(Checklist!$B$2:$B$151,"Company, users and platform",Checklist!$G$2:$G$151,"Blocked") -> 0 | E22: =COUNTIFS(Checklist!$B$2:$B$151,"Company, users and platform",Checklist!$G$2:$G$151,"Not tested") -> 9 | F22: =COUNTIF(Checklist!$B$2:$B$151,"Company, users and platform") -> 9
A23: Cross-cutting | B23: =COUNTIFS(Checklist!$B$2:$B$151,"Cross-cutting",Checklist!$G$2:$G$151,"Pass") -> 0 | C23: =COUNTIFS(Checklist!$B$2:$B$151,"Cross-cutting",Checklist!$G$2:$G$151,"Fail") -> 0 | D23: =COUNTIFS(Checklist!$B$2:$B$151,"Cross-cutting",Checklist!$G$2:$G$151,"Blocked") -> 0 | E23: =COUNTIFS(Checklist!$B$2:$B$151,"Cross-cutting",Checklist!$G$2:$G$151,"Not tested") -> 8 | F23: =COUNTIF(Checklist!$B$2:$B$151,"Cross-cutting") -> 8
A24: Known issues — do not report these | B24: =COUNTIFS(Checklist!$B$2:$B$151,"Known issues — do not report these",Checklist!$G$2:$G$151,"Pass") -> 0 | C24: =COUNTIFS(Checklist!$B$2:$B$151,"Known issues — do not report these",Checklist!$G$2:$G$151,"Fail") -> 0 | D24: =COUNTIFS(Checklist!$B$2:$B$151,"Known issues — do not report these",Checklist!$G$2:$G$151,"Blocked") -> 0 | E24: =COUNTIFS(Checklist!$B$2:$B$151,"Known issues — do not report these",Checklist!$G$2:$G$151,"Not tested") -> 0 | F24: =COUNTIF(Checklist!$B$2:$B$151,"Known issues — do not report these") -> 5
A26: Critical checks outstanding | B26: =COUNTIFS(Checklist!$F$2:$F$151,"*critical*",Checklist!$G$2:$G$151,"Not tested") -> 23
A29: Owner pass vs member pass | B29: Owner | C29: Member
A30: Pass | B30: =COUNTIF(Checklist!$G$2:$G$151,"Pass") -> 0 | C30: =COUNTIF(Checklist!$I$2:$I$151,"Pass") -> 0
A31: Fail | B31: =COUNTIF(Checklist!$G$2:$G$151,"Fail") -> 0 | C31: =COUNTIF(Checklist!$I$2:$I$151,"Fail") -> 0
A32: Blocked | B32: =COUNTIF(Checklist!$G$2:$G$151,"Blocked") -> 0 | C32: =COUNTIF(Checklist!$I$2:$I$151,"Blocked") -> 0
A33: Not tested | B33: =COUNTIF(Checklist!$G$2:$G$151,"Not tested") -> 0 | C33: =COUNTIF(Checklist!$I$2:$I$151,"Not tested") -> 0
A34: N/A | B34: =COUNTIF(Checklist!$G$2:$G$151,"N/A") -> 0 | C34: =COUNTIF(Checklist!$I$2:$I$151,"N/A") -> 0
A36: Critical (P0) still untested | B36: Owner | C36: Member
A37: Flagged critical | B37: =COUNTIFS(Checklist!$F$2:$F$151,"*critical*",Checklist!$G$2:$G$151,"Not tested") -> 0 | C37: =COUNTIFS(Checklist!$F$2:$F$151,"*critical*",Checklist!$I$2:$I$151,"Not tested") -> 0

Sheet Checklist
A1: ID | B1: Section | C1: Priority | D1: Check | E1: How to test | F1: Flags | G1: OWNER — result | H1: Expected for a MEMBER | I1: MEMBER — result | J1: Tester | K1: Date | L1: Notes
A2: PREP-01 | B2: Before you start | C2: Start | D2: Confirm the build under test | E2: Open the app and check the build id in the sidebar header. It should read 5ed3f48 or later. An older build means you are testing yesterday's bugs. | G2: Not tested | H2: Same. Do this setup on BOTH accounts before starting — the member pass is the one that finds anything. | I2: Not tested
A3: PREP-02 | B3: Before you start | C3: Start | D3: Have two accounts ready | E3: An owner account and a limited-role member in the same company. Permission gates cannot be tested from an owner account — everything passes. | F3: blocks permissions | G3: Not tested | H3: Same. Do this setup on BOTH accounts before starting — the member pass is the one that finds anything. | I3: Not tested
A4: PREP-03 | B4: Before you start | C4: Start | D4: Open the browser console and leave it open | E4: A red error in the console is a fail even when the screen looks right. Note the first error, not the tenth — later ones are usually consequences. | G4: Not tested | H4: Same. Do this setup on BOTH accounts before starting — the member pass is the one that finds anything. | I4: Not tested
A5: PREP-04 | B5: Before you start | C5: Start | D5: Decide what a fail means | E5: Fail = wrong result, lost data, a dead control, or a console error. Not a fail: anything in the Known issues section at the bottom. | G5: Not tested | H5: Same. Do this setup on BOTH accounts before starting — the member pass is the one that finds anything. | I5: Not tested
A6: SMOKE-01 | B6: Smoke — every route loads | C6: P0 | D6: /dashboard | E6: Loads, shows content (not an empty shell or a stuck loader), no console error. | G6: Not tested | H6: Only the routes the role can view may load. Every other route must be refused or redirected — never shown as an empty shell. Note in Notes which routes the role could reach. | I6: Not tested
A7: SMOKE-02 | B7: Smoke — every route loads | C7: P0 | D7: /workday | E7: Loads, shows content (not an empty shell or a stuck loader), no console error. | G7: Not tested | H7: Only the routes the role can view may load. Every other route must be refused or redirected — never shown as an empty shell. Note in Notes which routes the role could reach. | I7: Not tested
A8: SMOKE-03 | B8: Smoke — every route loads | C8: P0 | D8: /jobs | E8: Loads, shows content (not an empty shell or a stuck loader), no console error. | G8: Not tested | H8: Only the routes the role can view may load. Every other route must be refused or redirected — never shown as an empty shell. Note in Notes which routes the role could reach. | I8: Not tested
A9: SMOKE-04 | B9: Smoke — every route loads | C9: P0 | D9: /tasks | E9: Loads, shows content (not an empty shell or a stuck loader), no console error. | G9: Not tested | H9: Only the routes the role can view may load. Every other route must be refused or redirected — never shown as an empty shell. Note in Notes which routes the role could reach. | I9: Not tested
A10: SMOKE-05 | B10: Smoke — every route loads | C10: P0 | D10: /files | E10: Loads, shows content (not an empty shell or a stuck loader), no console error. | G10: Not tested | H10: Only the routes the role can view may load. Every other route must be refused or redirected — never shown as an empty shell. Note in Notes which routes the role could reach. | I10: Not tested
A11: SMOKE-06 | B11: Smoke — every route loads | C11: P0 | D11: /client-portals | E11: Loads, shows content (not an empty shell or a stuck loader), no console error. | G11: Not tested | H11: Only the routes the role can view may load. Every other route must be refused or redirected — never shown as an empty shell. Note in Notes which routes the role could reach. | I11: Not tested
A12: SMOKE-07 | B12: Smoke — every route loads | C12: P0 | D12: /workspaces | E12: Loads, shows content (not an empty shell or a stuck loader), no console error. | G12: Not tested | H12: Only the routes the role can view may load. Every other route must be refused or redirected — never shown as an empty shell. Note in Notes which routes the role could reach. | I12: Not tested
A13: SMOKE-08 | B13: Smoke — every route loads | C13: P0 | D13: /forms | E13: Loads, shows content (not an empty shell or a stuck loader), no console error. | G13: Not tested | H13: Only the routes the role can view may load. Every other route must be refused or redirected — never shown as an empty shell. Note in Notes which routes the role could reach. | I13: Not tested
A14: SMOKE-09 | B14: Smoke — every route loads | C14: P0 | D14: /analytics | E14: Loads, shows content (not an empty shell or a stuck loader), no console error. | G14: Not tested | H14: Only the routes the role can view may load. Every other route must be refused or redirected — never shown as an empty shell. Note in Notes which routes the role could reach. | I14: Not tested
A15: SMOKE-10 | B15: Smoke — every route loads | C15: P0 | D15: /crm | E15: Loads, shows content (not an empty shell or a stuck loader), no console error. | G15: Not tested | H15: Only the routes the role can view may load. Every other route must be refused or redirected — never shown as an empty shell. Note in Notes which routes the role could reach. | I15: Not tested
... A26: SMOKE-21 | B26: Smoke — every route loads | C26: P0 | D26: /team-chart | E26: Loads, shows content (not an empty shell or a stuck loader), no console error. | G26: Not tested | H26: Only the routes the role can view may load. Every other route must be refused or redirected — never shown as an empty shell. Note in Notes which routes the role could reach. | I26: Not tested
A27: NEW-01 | B27: Shipped in the last two days | C27: P1 | D27: Job saves with no client | E27: Add job → fill only the name → Save. Expect: it saves. This failed on a foreign key before; if it errors again, stop and report immediately. | F27: critical, new, was broken | G27: Not tested | H27: Readable only with the matching .view. Anything that creates, edits or deletes needs the matching .manage — without it the control must be ABSENT, not present and refusing. | I27: Not tested
A28: NEW-02 | B28: Shipped in the last two days | C28: P1 | D28: Clear activity log — wrong password refused | E28: Configure workspace → Clear log → enter a wrong password → Clear. Expect: "Incorrect password", log untouched. | F28: critical, new, destructive | G28: Not tested | H28: Readable only with the matching .view. Anything that creates, edits or deletes needs the matching .manage — without it the control must be ABSENT, not present and refusing. | I28: Not tested
A29: NEW-03 | B29: Shipped in the last two days | C29: P1 | D29: Clear activity log — correct password works | E29: Repeat with the right password. Expect: log cleared, exactly one entry left saying who cleared it and how many went. | F29: critical, new, destructive | G29: Not tested | H29: Readable only with the matching .view. Anything that creates, edits or deletes needs the matching .manage — without it the control must be ABSENT, not present and refusing. | I29: Not tested
A30: NEW-04 | B30: Shipped in the last two days | C30: P1 | D30: Clearing the log leaves the feed alone | E30: After clearing, check the workspace Activity feed. Expect: posts, files and links are all still there. Only the action log is cleared. | G30: Not tested | H30: Readable only with the matching .view. Anything that creates, edits or deletes needs the matching .manage — without it the control must be ABSENT, not present and refusing. | I30: Not tested
A31: NEW-05 | B31: Shipped in the last two days | C31: P1 | D31: The password field is typeable | E31: Click into the password box and type. Expect: characters appear in it. Previously keystrokes were stolen by the command palette. | F31: was broken | G31: Not tested | H31: Readable only with the matching .view. Anything that creates, edits or deletes needs the matching .manage — without it the control must be ABSENT, not present and refusing. | I31: Not tested
A32: NEW-06 | B32: Shipped in the last two days | C32: P1 | D32: Configure workspace header | E32: Expect: Clear log, Save workspace and Close along the top; no Cancel button at the bottom. | F32: new | G32: Not tested | H32: Readable only with the matching .view. Anything that creates, edits or deletes needs the matching .manage — without it the control must be ABSENT, not present and refusing. | I32: Not tested
A33: NEW-07 | B33: Shipped in the last two days | C33: P1 | D33: Enter still saves | E33: In Configure workspace, put the cursor in the name field and press Enter. Expect: it saves, same as clicking Save. | G33: Not tested | H33: Readable only with the matching .view. Anything that creates, edits or deletes needs the matching .manage — without it the control must be ABSENT, not present and refusing. | I33: Not tested
A34: NEW-08 | B34: Shipped in the last two days | C34: P1 | D34: Saving a workspace stays put | E34: Rename a workspace from the sidebar gear while on the Activity page. Expect: you stay on Activity. It used to throw you to Settings. | F34: was broken | G34: Not tested | H34: Readable only with the matching .view. Anything that creates, edits or deletes needs the matching .manage — without it the control must be ABSENT, not present and refusing. | I34: Not tested
A35: NEW-09 | B35: Shipped in the last two days | C35: P1 | D35: Activity log shows date and time | E35: Expect: each entry reads like "Aug 3, 2026 · 10:52 AM" followed by the relative time. | F35: new | G35: Not tested | H35: Readable only with the matching .view. Anything that creates, edits or deletes needs the matching .manage — without it the control must be ABSENT, not present and refusing. | I35: Not tested
A36: NEW-10 | B36: Shipped in the last two days | C36: P1 | D36: Select one job and delete it | E36: Jobs → List → tick one row → Delete 1. Expect: password prompt, then it goes to the Recycle Bin. | F36: critical, new, destructive | G36: Not tested | H36: Readable only with the matching .view. Anything that creates, edits or deletes needs the matching .manage — without it the control must be ABSENT, not present and refusing. | I36: Not tested
A37: NEW-11 | B37: Shipped in the last two days | C37: P1 | D37: Select several jobs and delete them | E37: Tick three → Delete 3. Expect: a progress bar counting "1 of 3", "2 of 3", then all three in the Recycle Bin. | F37: critical, new, destructive | G37: Not tested | H37: Readable only with the matching .view. Anything that creates, edits or deletes needs the matching .manage — without it the control must be ABSENT, not present and refusing. | I37: Not tested
A38: NEW-12 | B38: Shipped in the last two days | C38: P1 | D38: Deleted jobs restore | E38: Recycle Bin → restore them. Expect: they return to the Jobs list intact. | F38: critical | G38: Not tested | H38: Readable only with the matching .view. Anything that creates, edits or deletes needs the matching .manage — without it the control must be ABSENT, not present and refusing. | I38: Not tested
A39: NEW-13 | B39: Shipped in the last two days | C39: P1 | D39: Select-all respects the filter | E39: Filter the Jobs list, tick select-all, clear the filter. Expect: only the filtered rows are ticked. | G39: Not tested | H39: Readable only with the matching .view. Anything that creates, edits or deletes needs the matching .manage — without it the control must be ABSENT, not present and refusing. | I39: Not tested
A40: NEW-14 | B40: Shipped in the last two days | C40: P1 | D40: Ticking a row does not open the job | E40: Click a row's checkbox. Expect: it ticks and you stay on the list. | G40: Not tested | H40: Readable only with the matching .view. Anything that creates, edits or deletes needs the matching .manage — without it the control must be ABSENT, not present and refusing. | I40: Not tested
A41: NEW-15 | B41: Shipped in the last two days | C41: P1 | D41: Bulk delete is hidden from a limited role | E41: As the limited account, select jobs. Expect: no Delete button. | F41: critical, permissions | G41: Not tested | H41: Readable only with the matching .view. Anything that creates, edits or deletes needs the matching .manage — without it the control must be ABSENT, not present and refusing. | I41: Not tested
A42: NEW-16 | B42: Shipped in the last two days | C42: P1 | D42: Only one scrollbar | E42: On the dashboard and workspaces pages. Expect: one scrollbar on the content, none on the window. | F42: was broken | G42: Not tested | H42: Readable only with the matching .view. Anything that creates, edits or deletes needs the matching .manage — without it the control must be ABSENT, not present and refusing. | I42: Not tested
A43: NEW-17 | B43: Shipped in the last two days | C43: P1 | D43: App strip drag | E43: Workspaces → hold left button on the app strip and drag. Expect: it pans and glides to a stop; a click still opens an app. | G43: Not tested | H43: Readable only with the matching .view. Anything that creates, edits or deletes needs the matching .manage — without it the control must be ABSENT, not present and refusing. | I43: Not tested
A44: NEW-18 | B44: Shipped in the last two days | C44: P1 | D44: App strip keeps its place | E44: Scroll the app strip sideways, then click an app. Expect: the strip stays where you left it. | G44: Not tested | H44: Readable only with the matching .view. Anything that creates, edits or deletes needs the matching .manage — without it the control must be ABSENT, not present and refusing. | I44: Not tested
A45: NEW-19 | B45: Shipped in the last two days | C45: P1 | D45: Command palette over a dialog | E45: Open any dialog, press Ctrl+K. Expect: the palette does not open over it. | F45: was broken | G45: Not tested | H45: Readable only with the matching .view. Anything that creates, edits or deletes needs the matching .manage — without it the control must be ABSENT, not present and refusing. | I45: Not tested
A46: NEW-20 | B46: Shipped in the last two days | C46: P1 | D46: Sidebar themes and icon packs | E46: Settings → Appearance → try each sidebar theme and icon pack. Expect: icons all render (no blank squares), text stays readable on every theme. | F46: new | G46: Not tested | H46: Readable only with the matching .view. Anything that creates, edits or deletes needs the matching .manage — without it the control must be ABSENT, not present and refusing. | I46: Not tested
A47: NEW-21 | B47: Shipped in the last two days | C47: P1 | D47: Appearance is per-account | E47: Change your sidebar theme, then check the limited account. Expect: their appearance is unchanged. | G47: Not tested | H47: Readable only with the matching .view. Anything that creates, edits or deletes needs the matching .manage — without it the control must be ABSENT, not present and refusing. | I47: Not tested
A48: DEL-01 | B48: Destructive and password-gated | C48: P1 | D48: Recycle-bin deletes across records | E48: Delete one of each: contact, job, quote, task, file, form, client portal, knowledge article. Expect: each confirms first, then appears in the Recycle Bin. | F48: critical | G48: Not tested | H48: Not offered at all. A member reaching a destructive control is a security failure, not a cosmetic one — raise it as P0. | I48: Not tested
A49: DEL-02 | B49: Destructive and password-gated | C49: P1 | D49: Restore from the Recycle Bin | E49: Restore each one. Expect: the record comes back where it was, with its fields intact. | F49: critical | G49: Not tested | H49: Not offered at all. A member reaching a destructive control is a security failure, not a cosmetic one — raise it as P0. | I49: Not tested
A50: DEL-03 | B50: Destructive and password-gated | C50: P1 | D50: Undo immediately after deleting | E50: Delete a record and use the undo on the toast. Expect: it comes straight back. | F50: undo-recycle-delete | G50: Not tested | H50: Not offered at all. A member reaching a destructive control is a security failure, not a cosmetic one — raise it as P0. | I50: Not tested
A51: DEL-04 | B51: Destructive and password-gated | C51: P1 | D51: Permanent delete really is permanent | E51: Recycle Bin → permanently delete one item. Expect: a distinct, stronger confirmation, then it is gone for good. | F51: critical, destructive | G51: Not tested | H51: Not offered at all. A member reaching a destructive control is a security failure, not a cosmetic one — raise it as P0. | I51: Not tested
A52: DEL-05 | B52: Destructive and password-gated | C52: P1 | D52: Empty expired items | E52: Expect: it confirms, and removes only expired items — not everything in the bin. | F52: critical, destructive | G52: Not tested | H52: Not offered at all. A member reaching a destructive control is a security failure, not a cosmetic one — raise it as P0. | I52: Not tested
A53: DEL-06 | B53: Destructive and password-gated | C53: P1 | D53: Delete a company | E53: Owner only. Expect: a confirmation that names the company and requires deliberate confirmation. Do this on a throwaway company, never a real one. | F53: critical, destructive | G53: Not tested | H53: Not offered at all. A member reaching a destructive control is a security failure, not a cosmetic one — raise it as P0. | I53: Not tested
A54: DEL-07 | B54: Destructive and password-gated | C54: P1 | D54: Revoke a client portal link | E54: Expect: the old public link stops working. Test the link in a private window before and after. | F54: critical, destructive | G54: Not tested | H54: Not offered at all. A member reaching a destructive control is a security failure, not a cosmetic one — raise it as P0. | I54: Not tested
A55: DEL-08 | B55: Destructive and password-gated | C55: P1 | D55: Regenerate a client portal link | E55: Expect: a new link works and the old one does not. | G55: Not tested | H55: Not offered at all. A member reaching a destructive control is a security failure, not a cosmetic one — raise it as P0. | I55: Not tested
A56: DEL-09 | B56: Destructive and password-gated | C56: P1 | D56: Revoke an invite | E56: Expect: the invite code no longer lets anyone join. | G56: Not tested | H56: Not offered at all. A member reaching a destructive control is a security failure, not a cosmetic one — raise it as P0. | I56: Not tested
A57: DEL-10 | B57: Destructive and password-gated | C57: P1 | D57: Delete a role | E57: Expect: confirmation, and people holding that role are handled sensibly rather than left without access silently. | F57: critical | G57: Not tested | H57: Not offered at all. A member reaching a destructive control is a security failure, not a cosmetic one — raise it as P0. | I57: Not tested
A58: DEL-11 | B58: Destructive and password-gated | C58: P1 | D58: Delete a pipeline stage that has records | E58: Expect: it says how many records are affected, and offers to move them or clear the stage. Records are kept either way. | F58: critical | G58: Not tested | H58: Not offered at all. A member reaching a destructive control is a security failure, not a cosmetic one — raise it as P0. | I58: Not tested
A59: DEL-12 | B59: Destructive and password-gated | C59: P1 | D59: Reset dashboard layout | E59: Expect: confirmation, then default widgets return. | G59: Not tested | H59: Not offered at all. A member reaching a destructive control is a security failure, not a cosmetic one — raise it as P0. | I59: Not tested
A60: DEL-13 | B60: Destructive and password-gated | C60: P1 | D60: Reset appearance | E60: Expect: your own appearance returns to default and nobody else's changes. | G60: Not tested | H60: Not offered at all. A member reaching a destructive control is a security failure, not a cosmetic one — raise it as P0. | I60: Not tested
A61: DEL-14 | B61: Destructive and password-gated | C61: P1 | D61: Every destructive action as a limited role | E61: Repeat the deletes above as the limited account. Expect: refused or not offered — never a silent failure that looks like success. | F61: critical, permissions | G61: Not tested | H61: Not offered at all. A member reaching a destructive control is a security failure, not a cosmetic one — raise it as P0. | I61: Not tested
A62: CRM-01 | B62: Quest CRM | C62: Modules | D62: Contacts — full loop | E62: Create → edit → change stage → add a note and a task → delete. 33 actions live here, the largest surface in the app. | F62: 33 actions | G62: Not tested | H62: Needs crm.view to appear at all. Add, edit, import, merge and delete need crm.manage — absent without it. | I62: Not tested
A63: CRM-02 | B63: Quest CRM | C63: Modules | D63: Contacts — bulk and import | E63: Select several → label, campaign, email. Then import a small CSV and run dedupe. | G63: Not tested | H63: Needs crm.view to appear at all. Add, edit, import, merge and delete need crm.manage — absent without it. | I63: Not tested
A64: CRM-03 | B64: Quest CRM | C64: Modules | D64: Contacts — convert to quote | E64: Expect: the quote carries the contact's details across. | G64: Not tested | H64: Needs crm.view to appear at all. Add, edit, import, merge and delete need crm.manage — absent without it. | I64: Not tested
A65: CRM-04 | B65: Quest CRM | C65: Modules | D65: Jobs — full loop | E65: Create → edit → move stage on the board → open the record → add photos → delete. | F65: 15 actions | G65: Not tested | H65: Needs crm.view to appear at all. Add, edit, import, merge and delete need crm.manage — absent without it. | I65: Not tested
A66: CRM-05 | B66: Quest CRM | C66: Modules | D66: Jobs — board drag | E66: Drag a job between pipeline stages. Expect: the stage sticks after a refresh, and any stage automation fires. | G66: Not tested | H66: Needs crm.view to appear at all. Add, edit, import, merge and delete need crm.manage — absent without it. | I66: Not tested
A67: CRM-06 | B67: Quest CRM | C67: Modules | D67: Quotes — full loop | E67: Create → add and remove line items → change stage → convert to job. | F67: 9 actions | G67: Not tested | H67: Needs crm.view to appear at all. Add, edit, import, merge and delete need crm.manage — absent without it. | I67: Not tested
A68: CRM-07 | B68: Quest CRM | C68: Modules | D68: Proposals — build and share | E68: Open the builder → edit → copy the public link → open it in a private window → export. | F68: 8 actions | G68: Not tested | H68: Needs crm.view to appear at all. Add, edit, import, merge and delete need crm.manage — absent without it. | I68: Not tested
A69: CRM-08 | B69: Quest CRM | C69: Modules | D69: Workday | E69: Work through the next-step flow: open an item, complete it, skip one, use a quick action. | G69: Not tested | H69: Needs crm.view to appear at all. Add, edit, import, merge and delete need crm.manage — absent without it. | I69: Not tested
A70: CRM-09 | B70: Quest CRM | C70: Modules | D70: Record history | E70: Open History on a contact, job and quote. Expect: it loads against the right record and shows changes, or an honest empty state. | G70: Not tested | H70: Needs crm.view to appear at all. Add, edit, import, merge and delete need crm.manage — absent without it. | I70: Not tested
A71: WS-01 | B71: Workspace and App Builder | C71: Modules | D71: App Builder — create an app | E71: New app → add fields of several types → add records → edit → delete. | F71: 36 actions | G71: Not tested | H71: Needs workspaces.view to appear. Customize, Add card, Add app, the field builder, sub-item edits and Settings all need workspaces.manage — absent without it. | I71: Not tested
A72: WS-02 | B72: Workspace and App Builder | C72: Modules | D72: Field types round-trip | E72: Add one of each field type, fill it, save, reopen. Expect: every value comes back exactly as entered. | F72: critical | G72: Not tested | H72: Needs workspaces.view to appear. Customize, Add card, Add app, the field builder, sub-item edits and Settings all need workspaces.manage — absent without it. | I72: Not tested
A73: WS-03 | B73: Workspace and App Builder | C73: Modules | D73: Pipeline stages | E73: Manage stages → add, rename, reorder, recolour, delete. Expect: board columns follow. | G73: Not tested | H73: Needs workspaces.view to appear. Customize, Add card, Add app, the field builder, sub-item edits and Settings all need workspaces.manage — absent without it. | I73: Not tested
A74: WS-04 | B74: Workspace and App Builder | C74: Modules | D74: Board view | E74: Switch to board, drag records between columns. Expect: no jump back to the top after a drop. | F74: was broken | G74: Not tested | H74: Needs workspaces.view to appear. Customize, Add card, Add app, the field builder, sub-item edits and Settings all need workspaces.manage — absent without it. | I74: Not tested
A75: WS-05 | B75: Workspace and App Builder | C75: Modules | D75: Stage automations | E75: Create a rule on a stage change, trigger it. Expect: it fires once, on the change only — not on every save. | G75: Not tested | H75: Needs workspaces.view to appear. Customize, Add card, Add app, the field builder, sub-item edits and Settings all need workspaces.manage — absent without it. | I75: Not tested
A76: WS-06 | B76: Workspace and App Builder | C76: Modules | D76: Cross-company app install | E76: Install an app into another company you own: pick company, pick workspace. Expect: it lands in the right place. | F76: new | G76: Not tested | H76: Needs workspaces.view to appear. Customize, Add card, Add app, the field builder, sub-item edits and Settings all need workspaces.manage — absent without it. | I76: Not tested
A77: WS-07 | B77: Workspace and App Builder | C77: Modules | D77: Import and export | E77: Export an app's records to CSV, print, then re-import. Expect: Download, Export, Import and Print all work. | F77: was broken | G77: Not tested | H77: Needs workspaces.view to appear. Customize, Add card, Add app, the field builder, sub-item edits and Settings all need workspaces.manage — absent without it. | I77: Not tested
A78: WS-08 | B78: Workspace and App Builder | C78: Modules | D78: Reports tab | E78: Expect: charts render with correct totals — and an empty app reports zero, not one. | G78: Not tested | H78: Needs workspaces.view to appear. Customize, Add card, Add app, the field builder, sub-item edits and Settings all need workspaces.manage — absent without it. | I78: Not tested
A79: WS-09 | B79: Workspace and App Builder | C79: Modules | D79: Workspace backups | E79: Create a backup, download it, restore it. Expect: the restore returns the structure intact. | F79: critical | G79: Not tested | H79: Needs workspaces.view to appear. Customize, Add card, Add app, the field builder, sub-item edits and Settings all need workspaces.manage — absent without it. | I79: Not tested
A80: WS-10 | B80: Workspace and App Builder | C80: Modules | D80: Forms | E80: Build a form → add questions and options → preview → publish → submit it publicly → read the response → create a contact/task/job from it. | F80: 40 actions | G80: Not tested | H80: Needs workspaces.view to appear. Customize, Add card, Add app, the field builder, sub-item edits and Settings all need workspaces.manage — absent without it. | I80: Not tested
A81: WS-11 | B81: Workspace and App Builder | C81: Modules | D81: Client portals | E81: Create → upload a document → annotate, place markers, zoom, undo/redo → comment → export. | F81: 34 actions | G81: Not tested | H81: Needs workspaces.view to appear. Customize, Add card, Add app, the field builder, sub-item edits and Settings all need workspaces.manage — absent without it. | I81: Not tested
A82: OPS-01 | B82: Operations, finance and estimating | C82: Modules | D82: Files and Drive | E82: Upload → move → copy → select several → transfer → download → delete. | F82: 16 actions | G82: Not tested | H82: Each module needs its own .view (finance.view, eod.view, price_book…). Editing needs the matching .manage. Figures must not be visible at all without the .view. | I82: Not tested
A83: OPS-02 | B83: Operations, finance and estimating | C83: Modules | D83: Finance | E83: Create an invoice, an expense, a payment and a vendor; edit each. | F83: 7 actions | G83: Not tested | H83: Each module needs its own .view (finance.view, eod.view, price_book…). Editing needs the matching .manage. Figures must not be visible at all without the .view. | I83: Not tested
A84: OPS-03 | B84: Operations, finance and estimating | C84: Modules | D84: Price Book | E84: Add a vendor and material → edit cost → sort → categorise → import → delete a row. | F84: 13 actions | G84: Not tested | H84: Each module needs its own .view (finance.view, eod.view, price_book…). Editing needs the matching .manage. Figures must not be visible at all without the .view. | I84: Not tested
A85: OPS-04 | B85: Operations, finance and estimating | C85: Modules | D85: Calendar | E85: Add an event → edit → move between views → change scope → delete. | F85: 9 actions | G85: Not tested | H85: Each module needs its own .view (finance.view, eod.view, price_book…). Editing needs the matching .manage. Figures must not be visible at all without the .view. | I85: Not tested
A86: OPS-05 | B86: Operations, finance and estimating | C86: Modules | D86: Time and clock | E86: Clock in, clock out. Expect: the entry lands with the right duration on the clock dashboard. | G86: Not tested | H86: Each module needs its own .view (finance.view, eod.view, price_book…). Editing needs the matching .manage. Figures must not be visible at all without the .view. | I86: Not tested
A87: OPS-06 | B87: Operations, finance and estimating | C87: Modules | D87: Approvals | E87: Submit something for approval, then approve and reject as the right role. | G87: Not tested | H87: Each module needs its own .view (finance.view, eod.view, price_book…). Editing needs the matching .manage. Figures must not be visible at all without the .view. | I87: Not tested
A88: OPS-07 | B88: Operations, finance and estimating | C88: Modules | D88: EOD reports | E88: Write, edit, review and export a report to CSV. | G88: Not tested | H88: Each module needs its own .view (finance.view, eod.view, price_book…). Editing needs the matching .manage. Figures must not be visible at all without the .view. | I88: Not tested
A89: OPS-08 | B89: Operations, finance and estimating | C89: Modules | D89: Team workload and team chart | E89: Expect: both render with real people and no console error. | G89: Not tested | H89: Each module needs its own .view (finance.view, eod.view, price_book…). Editing needs the matching .manage. Figures must not be visible at all without the .view. | I89: Not tested
A90: OPS-09 | B90: Operations, finance and estimating | C90: Modules | D90: Knowledge base | E90: Create → edit → delete an article. | F90: 5 actions | G90: Not tested | H90: Each module needs its own .view (finance.view, eod.view, price_book…). Editing needs the matching .manage. Figures must not be visible at all without the .view. | I90: Not tested
A91: OPS-10 | B91: Operations, finance and estimating | C91: Modules | D91: Tasks | E91: Create from several places (record, palette, workspace), complete, delete. Check a recurring task rolls forward. | G91: Not tested | H91: Each module needs its own .view (finance.view, eod.view, price_book…). Editing needs the matching .manage. Figures must not be visible at all without the .view. | I91: Not tested
A92: MSG-01 | B92: Messages, notifications and search | C92: Modules | D92: Direct messages | E92: Start a new direct message, send, attach a file, edit, delete. | F92: 23 actions | G92: Not tested | H92: Needs messages.view. Sending needs messages.send. Deleting somebody else’s message needs messages.delete_any. Search must never return a record the role cannot open. | I92: Not tested
A93: MSG-02 | B93: Messages, notifications and search | C93: Modules | D93: Group messages | E93: Create a group, set its icon, manage members. | G93: Not tested | H93: Needs messages.view. Sending needs messages.send. Deleting somebody else’s message needs messages.delete_any. Search must never return a record the role cannot open. | I93: Not tested
A94: MSG-03 | B94: Messages, notifications and search | C94: Modules | D94: Message dock | E94: Open the floating dock, switch tabs, open a conversation, minimise, close. | G94: Not tested | H94: Needs messages.view. Sending needs messages.send. Deleting somebody else’s message needs messages.delete_any. Search must never return a record the role cannot open. | I94: Not tested
A95: MSG-04 | B95: Messages, notifications and search | C95: Modules | D95: Presence ring | E95: Expect: a green ring on people who are online, grey on those who are not. | G95: Not tested | H95: Needs messages.view. Sending needs messages.send. Deleting somebody else’s message needs messages.delete_any. Search must never return a record the role cannot open. | I95: Not tested
A96: MSG-05 | B96: Messages, notifications and search | C96: Modules | D96: Notifications | E96: Open the bell, open an item, mark all read. | G96: Not tested | H96: Needs messages.view. Sending needs messages.send. Deleting somebody else’s message needs messages.delete_any. Search must never return a record the role cannot open. | I96: Not tested
A97: MSG-06 | B97: Messages, notifications and search | C97: Modules | D97: Command palette | E97: Ctrl+K → search a record → run a command → create a task and a contact from it. | G97: Not tested | H97: Needs messages.view. Sending needs messages.send. Deleting somebody else’s message needs messages.delete_any. Search must never return a record the role cannot open. | I97: Not tested
A98: MSG-07 | B98: Messages, notifications and search | C98: Modules | D98: Global search | E98: Type in the topbar search. Expect: the palette opens with your text carried in. | G98: Not tested | H98: Needs messages.view. Sending needs messages.send. Deleting somebody else’s message needs messages.delete_any. Search must never return a record the role cannot open. | I98: Not tested
A99: ADM-01 | B99: Company, users and platform | C99: Modules | D99: Users and invites | E99: Send an invite, copy the code and link, revoke it. Approve and reject a join request. | F99: 11 actions | G99: Not tested | H99: Users needs users.view, and changing anything needs users.manage. Roles and Settings likewise. A member must never be able to widen its own role. | I99: Not tested
A100: ADM-02 | B100: Company, users and platform | C100: Modules | D100: Roles and permissions | E100: Create a role, set permissions, assign it, then use "View as role" to check what that person sees. | F100: critical | G100: Not tested | H100: Users needs users.view, and changing anything needs users.manage. Roles and Settings likewise. A member must never be able to widen its own role. | I100: Not tested
A101: ADM-03 | B101: Company, users and platform | C101: Modules | D101: Settings sweep | E101: Work through every settings tab. Expect: no blank page on any of them. | F101: was broken | G101: Not tested | H101: Users needs users.view, and changing anything needs users.manage. Roles and Settings likewise. A member must never be able to widen its own role. | I101: Not tested
A102: ADM-04 | B102: Company, users and platform | C102: Modules | D102: Company switching | E102: Switch between companies. Expect: data changes completely — no records leak between them. | F102: critical | G102: Not tested | H102: Users needs users.view, and changing anything needs users.manage. Roles and Settings likewise. A member must never be able to widen its own role. | I102: Not tested
A103: ADM-05 | B103: Company, users and platform | C103: Modules | D103: Create a company with a new name | E103: Expect: it is created and you are its owner. | G103: Not tested | H103: Users needs users.view, and changing anything needs users.manage. Roles and Settings likewise. A member must never be able to widen its own role. | I103: Not tested
A104: ADM-06 | B104: Company, users and platform | C104: Modules | D104: Create a company with a duplicate name | E104: Expect (today): it saves, giving you two companies with the same name. This is current behaviour, not a bug — flag it if you want it blocked. | G104: Not tested | H104: Users needs users.view, and changing anything needs users.manage. Roles and Settings likewise. A member must never be able to widen its own role. | I104: Not tested
A105: ADM-07 | B105: Company, users and platform | C105: Modules | D105: Master panel | E105: As the Lumen master account, open the Master section. Expect: it opens and lists companies. | F105: critical, was broken | G105: Not tested | H105: Users needs users.view, and changing anything needs users.manage. Roles and Settings likewise. A member must never be able to widen its own role. | I105: Not tested
A106: ADM-08 | B106: Company, users and platform | C106: Modules | D106: Profile and avatar | E106: Change your name, upload and crop an avatar. | G106: Not tested | H106: Users needs users.view, and changing anything needs users.manage. Roles and Settings likewise. A member must never be able to widen its own role. | I106: Not tested
A107: ADM-09 | B107: Company, users and platform | C107: Modules | D107: Sign out and back in | E107: Expect: you land where you should, with your company and workspace intact. | G107: Not tested | H107: Users needs users.view, and changing anything needs users.manage. Roles and Settings likewise. A member must never be able to widen its own role. | I107: Not tested
A108: X-01 | B108: Cross-cutting | C108: P1 | D108: Workspace scoping | E108: Switch workspace and check contacts, jobs, quotes, tasks and files. Expect: each shows only that workspace's records. | F108: critical | G108: Not tested | H108: Same behaviour, within what the role can reach. Nothing may leak a record, file or name from a module the role cannot view. | I108: Not tested
A109: X-02 | B109: Cross-cutting | C109: P1 | D109: Narrow window | E109: Resize to roughly half width and re-walk the dashboard, jobs and workspaces. Expect: nothing clipped, no sideways page scroll, still one scrollbar. | G109: Not tested | H109: Same behaviour, within what the role can reach. Nothing may leak a record, file or name from a module the role cannot view. | I109: Not tested
A110: X-03 | B110: Cross-cutting | C110: P1 | D110: Phone width | E110: Open on a phone or a 400px window. Expect: the mobile nav works and content is reachable. | G110: Not tested | H110: Same behaviour, within what the role can reach. Nothing may leak a record, file or name from a module the role cannot view. | I110: Not tested
...

Sheet Coverage
A1: Module | B1: Clickable actions
A2: Forms (build, publish, responses) | B2: 40
A3: Workspaces / App Builder | B3: 36
A4: Client portals | B4: 34
A5: Contacts | B5: 33
A6: Messages | B6: 23
A7: Dashboard | B7: 17
A8: Files / Drive | B8: 16
A9: Jobs | B9: 15
A10: Price Book | B10: 13
A11: Settings / Appearance | B11: 13
A12: Users, roles, invites | B12: 11
A13: Quotes | B13: 9
... A25: Total distinct actions | B25: 364
A27: Counted from the source: distinct data-action handlers per module. The checklist covers each module’s core loop rather than all 364 individually; destructive paths are listed in full.
